{"gradeHistory":[{"semester":"Fall 2025","instructor":"Marco Gonzalez-Navarro","totalEnrolled":67,"distribution":{"aPlus":13,"a":6,"aMinus":4,"bPlus":2,"b":6,"bMinus":5,"cPlus":6,"c":4,"cMinus":3,"dPlus":3,"d":2,"dMinus":3,"f":3,"p":3,"np":4},"averageGPA":2.73},{"semester":"Fall 2024","instructor":"Michael Walker","totalEnrolled":69,"distribution":{"aPlus":9,"a":4,"aMinus":3,"bPlus":9,"b":4,"bMinus":6,"cPlus":8,"c":6,"cMinus":6,"dPlus":3,"d":3,"dMinus":1,"f":0,"p":3,"np":4},"averageGPA":2.729032258064516},{"semester":"Fall 2023","instructor":"Marco Gonzalez-Navarro","totalEnrolled":70,"distribution":{"aPlus":11,"a":5,"aMinus":8,"bPlus":5,"b":4,"bMinus":7,"cPlus":6,"c":7,"cMinus":4,"dPlus":3,"d":2,"dMinus":1,"f":2,"p":3,"np":2},"averageGPA":2.8030769230769232},{"semester":"Summer 2023","instructor":"Jeremy Magruder","totalEnrolled":28,"distribution":{"aPlus":3,"a":5,"aMinus":7,"bPlus":1,"b":1,"bMinus":2,"cPlus":2,"c":1,"cMinus":1,"dPlus":1,"d":0,"dMinus":1,"f":0,"p":2,"np":1},"averageGPA":3.196},{"semester":"Fall 2022","instructor":"Marco Gonzalez-Navarro","totalEnrolled":70,"distribution":{"aPlus":16,"a":6,"aMinus":4,"bPlus":18,"b":4,"bMinus":7,"cPlus":4,"c":0,"cMinus":0,"dPlus":1,"d":0,"dMinus":2,"f":1,"p":5,"np":2},"averageGPA":3.253968253968254},{"semester":"Summer 2022","instructor":"Jeffrey Perloff","totalEnrolled":15,"distribution":{"aPlus":7,"a":3,"aMinus":3,"bPlus":2,"b":0,"bMinus":0,"cPlus":0,"c":0,"cMinus":0,"dPlus":0,"d":0,"dMinus":0,"f":0,"p":0,"np":0},"averageGPA":3.8466666666666667},{"semester":"Spring 2022","instructor":"Benjamin Faber","totalEnrolled":25,"distribution":{"aPlus":2,"a":4,"aMinus":4,"bPlus":2,"b":2,"bMinus":3,"cPlus":0,"c":0,"cMinus":0,"dPlus":0,"d":0,"dMinus":0,"f":2,"p":6,"np":0},"averageGPA":3.1315789473684212},{"semester":"Fall 2021","instructor":"Marco Gonzalez-Navarro","totalEnrolled":45,"distribution":{"aPlus":10,"a":1,"aMinus":6,"bPlus":7,"b":3,"bMinus":0,"cPlus":4,"c":1,"cMinus":1,"dPlus":1,"d":1,"dMinus":1,"f":1,"p":7,"np":1},"averageGPA":3.0864864864864865},{"semester":"Summer 2021","instructor":"Todd Fitch","totalEnrolled":22,"distribution":{"aPlus":0,"a":6,"aMinus":5,"bPlus":3,"b":1,"bMinus":0,"cPlus":0,"c":0,"cMinus":0,"dPlus":0,"d":1,"dMinus":0,"f":1,"p":5,"np":0},"averageGPA":3.317647058823529},{"semester":"Spring 2021","instructor":"Benjamin Faber","totalEnrolled":14,"distribution":{"aPlus":1,"a":2,"aMinus":4,"bPlus":0,"b":1,"bMinus":1,"cPlus":1,"c":0,"cMinus":0,"dPlus":0,"d":0,"dMinus":0,"f":1,"p":3,"np":0},"averageGPA":3.1636363636363636},{"semester":"Fall 2020","instructor":"Marco Gonzalez-Navarro","totalEnrolled":57,"distribution":{"aPlus":7,"a":10,"aMinus":7,"bPlus":4,"b":1,"bMinus":0,"cPlus":3,"c":3,"cMinus":0,"dPlus":0,"d":0,"dMinus":2,"f":1,"p":14,"np":5},"averageGPA":3.273684210526316},{"semester":"Summer 2020","instructor":"Jeffrey Perloff","totalEnrolled":19,"distribution":{"aPlus":2,"a":7,"aMinus":1,"bPlus":3,"b":0,"bMinus":2,"cPlus":0,"c":0,"cMinus":0,"dPlus":0,"d":0,"dMinus":0,"f":1,"p":1,"np":2},"averageGPA":3.4375},{"semester":"Spring 2020","instructor":"Benjamin Faber","totalEnrolled":35,"distribution":{"aPlus":0,"a":3,"aMinus":1,"bPlus":0,"b":1,"bMinus":0,"cPlus":0,"c":0,"cMinus":0,"dPlus":0,"d":0,"dMinus":0,"f":0,"p":30,"np":0},"averageGPA":3.7399999999999998},{"semester":"Fall 2019","instructor":"Aprajit Mahajan","totalEnrolled":74,"distribution":{"aPlus":2,"a":16,"aMinus":16,"bPlus":10,"b":12,"bMinus":5,"cPlus":0,"c":2,"cMinus":2,"dPlus":0,"d":0,"dMinus":0,"f":0,"p":9,"np":0},"averageGPA":3.4015384615384616}],"enrollmentHistory":[{"day":1,"date":"2026-03-22","enrolledCount":0,"enrollmentPercent":0,"waitlistCount":0},{"day":4,"date":"2026-03-25","enrolledCount":0,"enrollmentPercent":0,"waitlistCount":0},{"day":5,"date":"2026-03-27","enrolledCount":0,"enrollmentPercent":0,"waitlistCount":0},{"day":13,"date":"2026-04-03","enrolledCount":0,"enrollmentPercent":0,"waitlistCount":0},{"day":18,"date":"2026-04-08","enrolledCount":0,"enrollmentPercent":0,"waitlistCount":0},{"day":23,"date":"2026-04-13","enrolledCount":1,"enrollmentPercent":1.4,"waitlistCount":0},{"day":23,"date":"2026-04-13","enrolledCount":2,"enrollmentPercent":2.9,"waitlistCount":0},{"day":23,"date":"2026-04-13","enrolledCount":3,"enrollmentPercent":4.3,"waitlistCount":0},{"day":23,"date":"2026-04-13","enrolledCount":3,"enrollmentPercent":4.3,"waitlistCount":0},{"day":23,"date":"2026-04-14","enrolledCount":4,"enrollmentPercent":5.7,"waitlistCount":0},{"day":23,"date":"2026-04-14","enrolledCount":4,"enrollmentPercent":5.7,"waitlistCount":0},{"day":24,"date":"2026-04-14","enrolledCount":6,"enrollmentPercent":8.6,"waitlistCount":0},{"day":24,"date":"2026-04-14","enrolledCount":7,"enrollmentPercent":10,"waitlistCount":0},{"day":24,"date":"2026-04-14","enrolledCount":8,"enrollmentPercent":11.4,"waitlistCount":0},{"day":24,"date":"2026-04-14","enrolledCount":10,"enrollmentPercent":14.3,"waitlistCount":0},{"day":24,"date":"2026-04-14","enrolledCount":12,"enrollmentPercent":17.1,"waitlistCount":0},{"day":24,"date":"2026-04-14","enrolledCount":11,"enrollmentPercent":15.7,"waitlistCount":0},{"day":24,"date":"2026-04-15","enrolledCount":12,"enrollmentPercent":17.1,"waitlistCount":0},{"day":25,"date":"2026-04-15","enrolledCount":13,"enrollmentPercent":18.6,"waitlistCount":0},{"day":25,"date":"2026-04-15","enrolledCount":14,"enrollmentPercent":20,"waitlistCount":0},{"day":25,"date":"2026-04-15","enrolledCount":16,"enrollmentPercent":22.9,"waitlistCount":0},{"day":26,"date":"2026-04-16","enrolledCount":17,"enrollmentPercent":24.3,"waitlistCount":0},{"day":26,"date":"2026-04-16","enrolledCount":18,"enrollmentPercent":25.7,"waitlistCount":0},{"day":26,"date":"2026-04-16","enrolledCount":19,"enrollmentPercent":27.1,"waitlistCount":0},{"day":26,"date":"2026-04-16","enrolledCount":22,"enrollmentPercent":31.4,"waitlistCount":0},{"day":26,"date":"2026-04-17","enrolledCount":23,"enrollmentPercent":32.9,"waitlistCount":0},{"day":27,"date":"2026-04-17","enrolledCount":24,"enrollmentPercent":34.3,"waitlistCount":0},{"day":27,"date":"2026-04-17","enrolledCount":25,"enrollmentPercent":35.7,"waitlistCount":0}],"enrollmentHistoryBySemester":{"Fall 2025":[{"day":1,"date":"2025-04-03","enrolledCount":74,"enrollmentPercent":108.8,"waitlistCount":0},{"day":2,"date":"2025-04-04","enrolledCount":0,"enrollmentPercent":0,"waitlistCount":0},{"day":13,"date":"2025-04-15","enrolledCount":3,"enrollmentPercent":4.3,"waitlistCount":2},{"day":15,"date":"2025-04-17","enrolledCount":19,"enrollmentPercent":27.1,"waitlistCount":2},{"day":16,"date":"2025-04-18","enrolledCount":24,"enrollmentPercent":34.3,"waitlistCount":3},{"day":17,"date":"2025-04-19","enrolledCount":26,"enrollmentPercent":37.1,"waitlistCount":7},{"day":18,"date":"2025-04-20","enrolledCount":26,"enrollmentPercent":37.1,"waitlistCount":8},{"day":19,"date":"2025-04-21","enrolledCount":25,"enrollmentPercent":35.7,"waitlistCount":8},{"day":20,"date":"2025-04-22","enrolledCount":29,"enrollmentPercent":41.4,"waitlistCount":13},{"day":21,"date":"2025-04-23","enrolledCount":30,"enrollmentPercent":42.9,"waitlistCount":14},{"day":22,"date":"2025-04-24","enrolledCount":30,"enrollmentPercent":42.9,"waitlistCount":13},{"day":23,"date":"2025-04-25","enrolledCount":31,"enrollmentPercent":44.3,"waitlistCount":12},{"day":24,"date":"2025-04-26","enrolledCount":30,"enrollmentPercent":42.9,"waitlistCount":13},{"day":27,"date":"2025-04-29","enrolledCount":29,"enrollmentPercent":41.4,"waitlistCount":13},{"day":30,"date":"2025-05-02","enrolledCount":29,"enrollmentPercent":41.4,"waitlistCount":14},{"day":33,"date":"2025-05-05","enrolledCount":30,"enrollmentPercent":42.9,"waitlistCount":15},{"day":34,"date":"2025-05-06","enrolledCount":32,"enrollmentPercent":45.7,"waitlistCount":15},{"day":41,"date":"2025-05-13","enrolledCount":35,"enrollmentPercent":50,"waitlistCount":17},{"day":42,"date":"2025-05-14","enrolledCount":36,"enrollmentPercent":51.4,"waitlistCount":17},{"day":44,"date":"2025-05-16","enrolledCount":37,"enrollmentPercent":52.9,"waitlistCount":17},{"day":45,"date":"2025-05-17","enrolledCount":38,"enrollmentPercent":54.3,"waitlistCount":17},{"day":47,"date":"2025-05-19","enrolledCount":39,"enrollmentPercent":55.7,"waitlistCount":17},{"day":50,"date":"2025-05-22","enrolledCount":39,"enrollmentPercent":55.7,"waitlistCount":20},{"day":51,"date":"2025-05-23","enrolledCount":42,"enrollmentPercent":60,"waitlistCount":17},{"day":52,"date":"2025-05-24","enrolledCount":44,"enrollmentPercent":62.9,"waitlistCount":16},{"day":55,"date":"2025-05-27","enrolledCount":44,"enrollmentPercent":62.9,"waitlistCount":17},{"day":56,"date":"2025-05-28","enrolledCount":44,"enrollmentPercent":62.9,"waitlistCount":18},{"day":57,"date":"2025-05-29","enrolledCount":48,"enrollmentPercent":68.6,"waitlistCount":14},{"day":61,"date":"2025-06-02","enrolledCount":49,"enrollmentPercent":70,"waitlistCount":14},{"day":62,"date":"2025-06-03","enrolledCount":49,"enrollmentPercent":70,"waitlistCount":12},{"day":70,"date":"2025-06-11","enrolledCount":48,"enrollmentPercent":68.6,"waitlistCount":12},{"day":71,"date":"2025-06-12","enrolledCount":49,"enrollmentPercent":70,"waitlistCount":12},{"day":75,"date":"2025-06-16","enrolledCount":48,"enrollmentPercent":68.6,"waitlistCount":13},{"day":105,"date":"2025-07-16","enrolledCount":48,"enrollmentPercent":68.6,"waitlistCount":16},{"day":106,"date":"2025-07-17","enrolledCount":48,"enrollmentPercent":68.6,"waitlistCount":15},{"day":107,"date":"2025-07-18","enrolledCount":48,"enrollmentPercent":68.6,"waitlistCount":16},{"day":108,"date":"2025-07-19","enrolledCount":54,"enrollmentPercent":77.1,"waitlistCount":10},{"day":111,"date":"2025-07-22","enrolledCount":55,"enrollmentPercent":78.6,"waitlistCount":14},{"day":114,"date":"2025-07-25","enrolledCount":56,"enrollmentPercent":80,"waitlistCount":16},{"day":115,"date":"2025-07-26","enrolledCount":57,"enrollmentPercent":81.4,"waitlistCount":17},{"day":116,"date":"2025-07-27","enrolledCount":60,"enrollmentPercent":85.7,"waitlistCount":14},{"day":117,"date":"2025-07-28","enrolledCount":61,"enrollmentPercent":87.1,"waitlistCount":14},{"day":118,"date":"2025-07-29","enrolledCount":68,"enrollmentPercent":97.1,"waitlistCount":15},{"day":119,"date":"2025-07-30","enrolledCount":68,"enrollmentPercent":97.1,"waitlistCount":17},{"day":120,"date":"2025-07-31","enrolledCount":68,"enrollmentPercent":97.1,"waitlistCount":19},{"day":121,"date":"2025-08-01","enrolledCount":68,"enrollmentPercent":97.1,"waitlistCount":17},{"day":122,"date":"2025-08-02","enrolledCount":68,"enrollmentPercent":97.1,"waitlistCount":16},{"day":124,"date":"2025-08-04","enrolledCount":68,"enrollmentPercent":97.1,"waitlistCount":17},{"day":125,"date":"2025-08-05","enrolledCount":67,"enrollmentPercent":95.7,"waitlistCount":18},{"day":126,"date":"2025-08-06","enrolledCount":67,"enrollmentPercent":95.7,"waitlistCount":17},{"day":129,"date":"2025-08-09","enrolledCount":67,"enrollmentPercent":95.7,"waitlistCount":16},{"day":134,"date":"2025-08-14","enrolledCount":67,"enrollmentPercent":95.7,"waitlistCount":17},{"day":139,"date":"2025-08-19","enrolledCount":67,"enrollmentPercent":95.7,"waitlistCount":20},{"day":140,"date":"2025-08-20","enrolledCount":70,"enrollmentPercent":100,"waitlistCount":17},{"day":142,"date":"2025-08-22","enrolledCount":70,"enrollmentPercent":100,"waitlistCount":16},{"day":145,"date":"2025-08-25","enrolledCount":70,"enrollmentPercent":100,"waitlistCount":15},{"day":146,"date":"2025-08-26","enrolledCount":70,"enrollmentPercent":100,"waitlistCount":16},{"day":147,"date":"2025-08-27","enrolledCount":70,"enrollmentPercent":100,"waitlistCount":15},{"day":148,"date":"2025-08-28","enrolledCount":70,"enrollmentPercent":100,"waitlistCount":16},{"day":149,"date":"2025-08-29","enrolledCount":69,"enrollmentPercent":98.6,"waitlistCount":13},{"day":152,"date":"2025-09-01","enrolledCount":69,"enrollmentPercent":98.6,"waitlistCount":14},{"day":153,"date":"2025-09-02","enrolledCount":69,"enrollmentPercent":98.6,"waitlistCount":16},{"day":154,"date":"2025-09-03","enrolledCount":71,"enrollmentPercent":101.4,"waitlistCount":13},{"day":155,"date":"2025-09-04","enrolledCount":71,"enrollmentPercent":101.4,"waitlistCount":9},{"day":157,"date":"2025-09-06","enrolledCount":72,"enrollmentPercent":102.9,"waitlistCount":8},{"day":158,"date":"2025-09-07","enrolledCount":72,"enrollmentPercent":102.9,"waitlistCount":9},{"day":160,"date":"2025-09-09","enrolledCount":71,"enrollmentPercent":101.4,"waitlistCount":8},{"day":161,"date":"2025-09-10","enrolledCount":71,"enrollmentPercent":101.4,"waitlistCount":7},{"day":163,"date":"2025-09-12","enrolledCount":73,"enrollmentPercent":104.3,"waitlistCount":4},{"day":164,"date":"2025-09-13","enrolledCount":73,"enrollmentPercent":104.3,"waitlistCount":1},{"day":165,"date":"2025-09-14","enrolledCount":72,"enrollmentPercent":102.9,"waitlistCount":1},{"day":167,"date":"2025-09-16","enrolledCount":70,"enrollmentPercent":100,"waitlistCount":1},{"day":168,"date":"2025-09-17","enrolledCount":69,"enrollmentPercent":98.6,"waitlistCount":1},{"day":169,"date":"2025-09-18","enrolledCount":70,"enrollmentPercent":100,"waitlistCount":0},{"day":171,"date":"2025-09-20","enrolledCount":71,"enrollmentPercent":101.4,"waitlistCount":0},{"day":219,"date":"2025-11-08","enrolledCount":71,"enrollmentPercent":101.4,"waitlistCount":0},{"day":223,"date":"2025-11-12","enrolledCount":71,"enrollmentPercent":101.4,"waitlistCount":0},{"day":228,"date":"2025-11-17","enrolledCount":71,"enrollmentPercent":101.4,"waitlistCount":0},{"day":230,"date":"2025-11-19","enrolledCount":71,"enrollmentPercent":101.4,"waitlistCount":0},{"day":230,"date":"2025-11-19","enrolledCount":71,"enrollmentPercent":101.4,"waitlistCount":0},{"day":231,"date":"2025-11-19","enrolledCount":71,"enrollmentPercent":101.4,"waitlistCount":0},{"day":231,"date":"2025-11-19","enrolledCount":71,"enrollmentPercent":101.4,"waitlistCount":0},{"day":256,"date":"2025-12-15","enrolledCount":71,"enrollmentPercent":101.4,"waitlistCount":0}],"Fall 2024":[{"day":1,"date":"2024-04-04","enrolledCount":0,"enrollmentPercent":0,"waitlistCount":0},{"day":20,"date":"2024-04-23","enrolledCount":5,"enrollmentPercent":7.4,"waitlistCount":0},{"day":21,"date":"2024-04-24","enrolledCount":27,"enrollmentPercent":39.7,"waitlistCount":4},{"day":22,"date":"2024-04-25","enrolledCount":42,"enrollmentPercent":61.8,"waitlistCount":6},{"day":23,"date":"2024-04-26","enrolledCount":51,"enrollmentPercent":75,"waitlistCount":11},{"day":24,"date":"2024-04-27","enrolledCount":52,"enrollmentPercent":76.5,"waitlistCount":15},{"day":25,"date":"2024-04-28","enrolledCount":53,"enrollmentPercent":77.9,"waitlistCount":15},{"day":26,"date":"2024-04-29","enrolledCount":53,"enrollmentPercent":77.9,"waitlistCount":14},{"day":27,"date":"2024-04-30","enrolledCount":54,"enrollmentPercent":79.4,"waitlistCount":17},{"day":28,"date":"2024-05-01","enrolledCount":54,"enrollmentPercent":79.4,"waitlistCount":19},{"day":29,"date":"2024-05-02","enrolledCount":55,"enrollmentPercent":80.9,"waitlistCount":20},{"day":31,"date":"2024-05-04","enrolledCount":56,"enrollmentPercent":82.4,"waitlistCount":20},{"day":34,"date":"2024-05-07","enrolledCount":56,"enrollmentPercent":82.4,"waitlistCount":21},{"day":35,"date":"2024-05-08","enrolledCount":55,"enrollmentPercent":80.9,"waitlistCount":21},{"day":43,"date":"2024-05-16","enrolledCount":57,"enrollmentPercent":83.8,"waitlistCount":21},{"day":46,"date":"2024-05-19","enrolledCount":57,"enrollmentPercent":83.8,"waitlistCount":22},{"day":50,"date":"2024-05-23","enrolledCount":57,"enrollmentPercent":83.8,"waitlistCount":23},{"day":52,"date":"2024-05-25","enrolledCount":57,"enrollmentPercent":83.8,"waitlistCount":22},{"day":53,"date":"2024-05-26","enrolledCount":57,"enrollmentPercent":83.8,"waitlistCount":21},{"day":55,"date":"2024-05-28","enrolledCount":58,"enrollmentPercent":85.3,"waitlistCount":22},{"day":56,"date":"2024-05-29","enrolledCount":60,"enrollmentPercent":88.2,"waitlistCount":21},{"day":58,"date":"2024-05-31","enrolledCount":62,"enrollmentPercent":91.2,"waitlistCount":20},{"day":59,"date":"2024-06-01","enrolledCount":63,"enrollmentPercent":92.6,"waitlistCount":20},{"day":62,"date":"2024-06-04","enrolledCount":62,"enrollmentPercent":91.2,"waitlistCount":20},{"day":64,"date":"2024-06-06","enrolledCount":63,"enrollmentPercent":92.6,"waitlistCount":19},{"day":65,"date":"2024-06-07","enrolledCount":64,"enrollmentPercent":94.1,"waitlistCount":19},{"day":68,"date":"2024-06-10","enrolledCount":64,"enrollmentPercent":94.1,"waitlistCount":20},{"day":136,"date":"2024-08-17","enrolledCount":70,"enrollmentPercent":102.9,"waitlistCount":26},{"day":137,"date":"2024-08-18","enrolledCount":70,"enrollmentPercent":102.9,"waitlistCount":25},{"day":138,"date":"2024-08-19","enrolledCount":70,"enrollmentPercent":102.9,"waitlistCount":26},{"day":139,"date":"2024-08-20","enrolledCount":68,"enrollmentPercent":100,"waitlistCount":28},{"day":141,"date":"2024-08-22","enrolledCount":68,"enrollmentPercent":100,"waitlistCount":30},{"day":144,"date":"2024-08-25","enrolledCount":68,"enrollmentPercent":100,"waitlistCount":29},{"day":146,"date":"2024-08-27","enrolledCount":68,"enrollmentPercent":100,"waitlistCount":31},{"day":148,"date":"2024-08-29","enrolledCount":68,"enrollmentPercent":100,"waitlistCount":24},{"day":149,"date":"2024-08-30","enrolledCount":68,"enrollmentPercent":100,"waitlistCount":22},{"day":150,"date":"2024-08-31","enrolledCount":68,"enrollmentPercent":100,"waitlistCount":21},{"day":154,"date":"2024-09-04","enrolledCount":69,"enrollmentPercent":101.5,"waitlistCount":18},{"day":155,"date":"2024-09-05","enrolledCount":69,"enrollmentPercent":101.5,"waitlistCount":16},{"day":156,"date":"2024-09-06","enrolledCount":70,"enrollmentPercent":102.9,"waitlistCount":15},{"day":157,"date":"2024-09-07","enrolledCount":69,"enrollmentPercent":101.5,"waitlistCount":16},{"day":160,"date":"2024-09-10","enrolledCount":68,"enrollmentPercent":100,"waitlistCount":16},{"day":161,"date":"2024-09-11","enrolledCount":71,"enrollmentPercent":104.4,"waitlistCount":13},{"day":162,"date":"2024-09-12","enrolledCount":70,"enrollmentPercent":102.9,"waitlistCount":13},{"day":163,"date":"2024-09-13","enrolledCount":70,"enrollmentPercent":102.9,"waitlistCount":12},{"day":164,"date":"2024-09-14","enrolledCount":70,"enrollmentPercent":102.9,"waitlistCount":11},{"day":167,"date":"2024-09-17","enrolledCount":71,"enrollmentPercent":104.4,"waitlistCount":10},{"day":168,"date":"2024-09-18","enrolledCount":71,"enrollmentPercent":104.4,"waitlistCount":9},{"day":169,"date":"2024-09-19","enrolledCount":73,"enrollmentPercent":107.4,"waitlistCount":7},{"day":170,"date":"2024-09-20","enrolledCount":73,"enrollmentPercent":107.4,"waitlistCount":0},{"day":175,"date":"2024-09-25","enrolledCount":74,"enrollmentPercent":108.8,"waitlistCount":0}],"Fall 2023":[{"day":1,"date":"2023-04-02","enrolledCount":0,"enrollmentPercent":0,"waitlistCount":0},{"day":17,"date":"2023-04-18","enrolledCount":4,"enrollmentPercent":5,"waitlistCount":0},{"day":18,"date":"2023-04-19","enrolledCount":6,"enrollmentPercent":7.5,"waitlistCount":0},{"day":19,"date":"2023-04-20","enrolledCount":20,"enrollmentPercent":25,"waitlistCount":0},{"day":20,"date":"2023-04-21","enrolledCount":32,"enrollmentPercent":40,"waitlistCount":0},{"day":21,"date":"2023-04-22","enrolledCount":46,"enrollmentPercent":57.5,"waitlistCount":6},{"day":24,"date":"2023-04-25","enrolledCount":47,"enrollmentPercent":58.8,"waitlistCount":7},{"day":25,"date":"2023-04-26","enrolledCount":48,"enrollmentPercent":60,"waitlistCount":7},{"day":27,"date":"2023-04-28","enrolledCount":49,"enrollmentPercent":61.3,"waitlistCount":7},{"day":28,"date":"2023-04-29","enrolledCount":49,"enrollmentPercent":61.3,"waitlistCount":5},{"day":32,"date":"2023-05-03","enrolledCount":49,"enrollmentPercent":61.3,"waitlistCount":6},{"day":44,"date":"2023-05-15","enrolledCount":49,"enrollmentPercent":61.3,"waitlistCount":8},{"day":45,"date":"2023-05-16","enrolledCount":49,"enrollmentPercent":61.3,"waitlistCount":9},{"day":46,"date":"2023-05-17","enrolledCount":50,"enrollmentPercent":62.5,"waitlistCount":9},{"day":48,"date":"2023-05-19","enrolledCount":51,"enrollmentPercent":63.8,"waitlistCount":8},{"day":51,"date":"2023-05-22","enrolledCount":52,"enrollmentPercent":65,"waitlistCount":8},{"day":52,"date":"2023-05-23","enrolledCount":53,"enrollmentPercent":66.3,"waitlistCount":8},{"day":55,"date":"2023-05-26","enrolledCount":54,"enrollmentPercent":67.5,"waitlistCount":7},{"day":56,"date":"2023-05-27","enrolledCount":55,"enrollmentPercent":68.8,"waitlistCount":7},{"day":61,"date":"2023-06-01","enrolledCount":56,"enrollmentPercent":70,"waitlistCount":7},{"day":62,"date":"2023-06-02","enrolledCount":56,"enrollmentPercent":70,"waitlistCount":8},{"day":65,"date":"2023-06-05","enrolledCount":55,"enrollmentPercent":68.8,"waitlistCount":8},{"day":67,"date":"2023-06-07","enrolledCount":55,"enrollmentPercent":68.8,"waitlistCount":7},{"day":73,"date":"2023-06-13","enrolledCount":55,"enrollmentPercent":68.8,"waitlistCount":6},{"day":75,"date":"2023-06-15","enrolledCount":54,"enrollmentPercent":67.5,"waitlistCount":6},{"day":77,"date":"2023-06-17","enrolledCount":54,"enrollmentPercent":67.5,"waitlistCount":7},{"day":102,"date":"2023-07-12","enrolledCount":56,"enrollmentPercent":70,"waitlistCount":8},{"day":103,"date":"2023-07-13","enrolledCount":56,"enrollmentPercent":70,"waitlistCount":7},{"day":104,"date":"2023-07-14","enrolledCount":62,"enrollmentPercent":77.5,"waitlistCount":1},{"day":105,"date":"2023-07-15","enrolledCount":62,"enrollmentPercent":77.5,"waitlistCount":2},{"day":107,"date":"2023-07-17","enrolledCount":63,"enrollmentPercent":78.8,"waitlistCount":1},{"day":108,"date":"2023-07-18","enrolledCount":67,"enrollmentPercent":83.8,"waitlistCount":1},{"day":109,"date":"2023-07-19","enrolledCount":68,"enrollmentPercent":85,"waitlistCount":1},{"day":110,"date":"2023-07-20","enrolledCount":70,"enrollmentPercent":87.5,"waitlistCount":1},{"day":111,"date":"2023-07-21","enrolledCount":71,"enrollmentPercent":88.8,"waitlistCount":1},{"day":112,"date":"2023-07-22","enrolledCount":73,"enrollmentPercent":91.3,"waitlistCount":3},{"day":114,"date":"2023-07-24","enrolledCount":73,"enrollmentPercent":91.3,"waitlistCount":5},{"day":115,"date":"2023-07-25","enrolledCount":73,"enrollmentPercent":91.3,"waitlistCount":4},{"day":116,"date":"2023-07-26","enrolledCount":73,"enrollmentPercent":91.3,"waitlistCount":8},{"day":118,"date":"2023-07-28","enrolledCount":72,"enrollmentPercent":90,"waitlistCount":10},{"day":119,"date":"2023-07-29","enrolledCount":73,"enrollmentPercent":91.3,"waitlistCount":11},{"day":120,"date":"2023-07-30","enrolledCount":73,"enrollmentPercent":91.3,"waitlistCount":12},{"day":125,"date":"2023-08-04","enrolledCount":73,"enrollmentPercent":91.3,"waitlistCount":14},{"day":130,"date":"2023-08-09","enrolledCount":73,"enrollmentPercent":91.3,"waitlistCount":15},{"day":132,"date":"2023-08-11","enrolledCount":73,"enrollmentPercent":91.3,"waitlistCount":16},{"day":133,"date":"2023-08-12","enrolledCount":73,"enrollmentPercent":100,"waitlistCount":16},{"day":134,"date":"2023-08-13","enrolledCount":73,"enrollmentPercent":100,"waitlistCount":18},{"day":139,"date":"2023-08-18","enrolledCount":73,"enrollmentPercent":100,"waitlistCount":16},{"day":140,"date":"2023-08-19","enrolledCount":73,"enrollmentPercent":100,"waitlistCount":15},{"day":141,"date":"2023-08-20","enrolledCount":73,"enrollmentPercent":100,"waitlistCount":14},{"day":142,"date":"2023-08-21","enrolledCount":73,"enrollmentPercent":100,"waitlistCount":15},{"day":143,"date":"2023-08-22","enrolledCount":73,"enrollmentPercent":100,"waitlistCount":14},{"day":144,"date":"2023-08-23","enrolledCount":72,"enrollmentPercent":98.6,"waitlistCount":13},{"day":145,"date":"2023-08-24","enrolledCount":73,"enrollmentPercent":100,"waitlistCount":9},{"day":146,"date":"2023-08-25","enrolledCount":73,"enrollmentPercent":100,"waitlistCount":10},{"day":149,"date":"2023-08-28","enrolledCount":73,"enrollmentPercent":100,"waitlistCount":9},{"day":151,"date":"2023-08-30","enrolledCount":73,"enrollmentPercent":100,"waitlistCount":8},{"day":152,"date":"2023-08-31","enrolledCount":75,"enrollmentPercent":102.7,"waitlistCount":5},{"day":153,"date":"2023-09-01","enrolledCount":73,"enrollmentPercent":100,"waitlistCount":0},{"day":158,"date":"2023-09-06","enrolledCount":72,"enrollmentPercent":98.6,"waitlistCount":0},{"day":159,"date":"2023-09-07","enrolledCount":73,"enrollmentPercent":100,"waitlistCount":0},{"day":166,"date":"2023-09-14","enrolledCount":72,"enrollmentPercent":98.6,"waitlistCount":0},{"day":167,"date":"2023-09-15","enrolledCount":73,"enrollmentPercent":100,"waitlistCount":0}]}}