{"gradeHistory":[{"semester":"Fall 2025","instructor":"Kimiko Ryokai","totalEnrolled":21,"distribution":{"aPlus":4,"a":15,"aMinus":0,"bPlus":1,"b":0,"bMinus":0,"cPlus":1,"c":0,"cMinus":0,"dPlus":0,"d":0,"dMinus":0,"f":0,"p":0,"np":0},"averageGPA":3.8857142857142852},{"semester":"Fall 2024","instructor":"Kimiko Ryokai","totalEnrolled":25,"distribution":{"aPlus":3,"a":20,"aMinus":0,"bPlus":0,"b":1,"bMinus":0,"cPlus":0,"c":0,"cMinus":0,"dPlus":0,"d":0,"dMinus":0,"f":0,"p":0,"np":0},"averageGPA":3.9583333333333335},{"semester":"Fall 2023","instructor":"Kimiko Ryokai","totalEnrolled":14,"distribution":{"aPlus":1,"a":12,"aMinus":0,"bPlus":0,"b":0,"bMinus":0,"cPlus":0,"c":0,"cMinus":0,"dPlus":0,"d":0,"dMinus":0,"f":0,"p":0,"np":0},"averageGPA":4},{"semester":"Fall 2022","instructor":"Christopher Myers","totalEnrolled":19,"distribution":{"aPlus":1,"a":13,"aMinus":2,"bPlus":0,"b":0,"bMinus":0,"cPlus":0,"c":0,"cMinus":1,"dPlus":0,"d":0,"dMinus":0,"f":0,"p":0,"np":0},"averageGPA":3.829411764705882},{"semester":"Fall 2021","instructor":"Kimiko Ryokai","totalEnrolled":27,"distribution":{"aPlus":1,"a":23,"aMinus":1,"bPlus":0,"b":0,"bMinus":0,"cPlus":0,"c":0,"cMinus":0,"dPlus":0,"d":0,"dMinus":0,"f":0,"p":0,"np":0},"averageGPA":3.988},{"semester":"Fall 2019","instructor":"Adam Hutz","totalEnrolled":17,"distribution":{"aPlus":2,"a":5,"aMinus":6,"bPlus":1,"b":0,"bMinus":0,"cPlus":0,"c":0,"cMinus":0,"dPlus":0,"d":0,"dMinus":0,"f":0,"p":0,"np":0},"averageGPA":3.8214285714285716}],"enrollmentHistory":[{"day":1,"date":"2026-03-22","enrolledCount":0,"enrollmentPercent":0,"waitlistCount":0},{"day":4,"date":"2026-03-25","enrolledCount":0,"enrollmentPercent":0,"waitlistCount":0},{"day":5,"date":"2026-03-27","enrolledCount":0,"enrollmentPercent":0,"waitlistCount":0},{"day":6,"date":"2026-03-28","enrolledCount":0,"enrollmentPercent":0,"waitlistCount":0},{"day":13,"date":"2026-04-03","enrolledCount":0,"enrollmentPercent":0,"waitlistCount":0},{"day":18,"date":"2026-04-08","enrolledCount":0,"enrollmentPercent":0,"waitlistCount":0},{"day":20,"date":"2026-04-11","enrolledCount":0,"enrollmentPercent":0,"waitlistCount":0},{"day":23,"date":"2026-04-13","enrolledCount":0,"enrollmentPercent":0,"waitlistCount":0},{"day":23,"date":"2026-04-14","enrolledCount":0,"enrollmentPercent":0,"waitlistCount":0}],"enrollmentHistoryBySemester":{}}