{"gradeHistory":[{"semester":"Summer 2025","instructor":"Idelle Cooper","totalEnrolled":67,"distribution":{"aPlus":0,"a":23,"aMinus":13,"bPlus":11,"b":9,"bMinus":5,"cPlus":0,"c":3,"cMinus":0,"dPlus":0,"d":2,"dMinus":0,"f":0,"p":1,"np":0},"averageGPA":3.4075757575757573},{"semester":"Fall 2024","instructor":"Michael Boots","totalEnrolled":193,"distribution":{"aPlus":24,"a":43,"aMinus":20,"bPlus":32,"b":16,"bMinus":26,"cPlus":7,"c":6,"cMinus":0,"dPlus":0,"d":0,"dMinus":2,"f":3,"p":8,"np":6},"averageGPA":3.3256983240223463},{"semester":"Summer 2024","instructor":"Idelle Cooper","totalEnrolled":69,"distribution":{"aPlus":0,"a":25,"aMinus":20,"bPlus":11,"b":4,"bMinus":1,"cPlus":2,"c":3,"cMinus":0,"dPlus":0,"d":2,"dMinus":0,"f":0,"p":1,"np":0},"averageGPA":3.4941176470588236},{"semester":"Summer 2023","instructor":"Idelle Cooper","totalEnrolled":61,"distribution":{"aPlus":0,"a":24,"aMinus":17,"bPlus":10,"b":3,"bMinus":1,"cPlus":4,"c":0,"cMinus":1,"dPlus":0,"d":0,"dMinus":0,"f":0,"p":0,"np":1},"averageGPA":3.5749999999999997},{"semester":"Fall 2022","instructor":"Michael Boots","totalEnrolled":122,"distribution":{"aPlus":20,"a":36,"aMinus":23,"bPlus":9,"b":13,"bMinus":7,"cPlus":3,"c":0,"cMinus":1,"dPlus":0,"d":0,"dMinus":0,"f":0,"p":9,"np":1},"averageGPA":3.6187499999999995},{"semester":"Summer 2022","instructor":"Idelle Cooper","totalEnrolled":44,"distribution":{"aPlus":3,"a":20,"aMinus":8,"bPlus":4,"b":1,"bMinus":2,"cPlus":0,"c":1,"cMinus":2,"dPlus":0,"d":0,"dMinus":0,"f":0,"p":2,"np":1},"averageGPA":3.6243902439024387},{"semester":"Summer 2021","instructor":"Idelle Cooper","totalEnrolled":25,"distribution":{"aPlus":0,"a":14,"aMinus":5,"bPlus":2,"b":1,"bMinus":0,"cPlus":0,"c":0,"cMinus":0,"dPlus":1,"d":1,"dMinus":0,"f":0,"p":1,"np":0},"averageGPA":3.5999999999999996},{"semester":"Spring 2021","instructor":"Michael Boots","totalEnrolled":129,"distribution":{"aPlus":16,"a":64,"aMinus":13,"bPlus":7,"b":5,"bMinus":1,"cPlus":0,"c":1,"cMinus":1,"dPlus":0,"d":0,"dMinus":0,"f":1,"p":17,"np":3},"averageGPA":3.7853211009174315},{"semester":"Summer 2020","instructor":"Idelle Cooper","totalEnrolled":15,"distribution":{"aPlus":1,"a":7,"aMinus":3,"bPlus":3,"b":1,"bMinus":0,"cPlus":0,"c":0,"cMinus":0,"dPlus":0,"d":0,"dMinus":0,"f":0,"p":0,"np":0},"averageGPA":3.7333333333333334},{"semester":"Spring 2020","instructor":"Michael Boots","totalEnrolled":145,"distribution":{"aPlus":0,"a":29,"aMinus":34,"bPlus":16,"b":4,"bMinus":5,"cPlus":0,"c":0,"cMinus":0,"dPlus":0,"d":0,"dMinus":0,"f":0,"p":57,"np":0},"averageGPA":3.6375}],"enrollmentHistory":[{"day":1,"date":"2026-03-22","enrolledCount":0,"enrollmentPercent":0,"waitlistCount":0},{"day":1,"date":"2026-03-23","enrolledCount":0,"enrollmentPercent":0,"waitlistCount":0},{"day":4,"date":"2026-03-25","enrolledCount":0,"enrollmentPercent":0,"waitlistCount":0},{"day":5,"date":"2026-03-27","enrolledCount":0,"enrollmentPercent":0,"waitlistCount":0},{"day":6,"date":"2026-03-28","enrolledCount":0,"enrollmentPercent":0,"waitlistCount":0},{"day":13,"date":"2026-04-03","enrolledCount":0,"enrollmentPercent":0,"waitlistCount":0},{"day":18,"date":"2026-04-08","enrolledCount":0,"enrollmentPercent":0,"waitlistCount":0},{"day":23,"date":"2026-04-13","enrolledCount":2,"enrollmentPercent":0.9,"waitlistCount":0},{"day":23,"date":"2026-04-13","enrolledCount":3,"enrollmentPercent":1.3,"waitlistCount":0},{"day":23,"date":"2026-04-13","enrolledCount":5,"enrollmentPercent":2.2,"waitlistCount":0},{"day":23,"date":"2026-04-13","enrolledCount":8,"enrollmentPercent":3.6,"waitlistCount":0},{"day":23,"date":"2026-04-13","enrolledCount":10,"enrollmentPercent":4.4,"waitlistCount":0},{"day":23,"date":"2026-04-13","enrolledCount":10,"enrollmentPercent":4.4,"waitlistCount":0},{"day":23,"date":"2026-04-13","enrolledCount":12,"enrollmentPercent":5.3,"waitlistCount":0},{"day":23,"date":"2026-04-13","enrolledCount":12,"enrollmentPercent":5.3,"waitlistCount":0},{"day":23,"date":"2026-04-14","enrolledCount":13,"enrollmentPercent":5.8,"waitlistCount":0},{"day":23,"date":"2026-04-14","enrolledCount":14,"enrollmentPercent":6.2,"waitlistCount":0},{"day":24,"date":"2026-04-14","enrolledCount":15,"enrollmentPercent":6.7,"waitlistCount":0},{"day":24,"date":"2026-04-14","enrolledCount":18,"enrollmentPercent":8,"waitlistCount":0},{"day":24,"date":"2026-04-14","enrolledCount":19,"enrollmentPercent":8.4,"waitlistCount":0},{"day":24,"date":"2026-04-14","enrolledCount":23,"enrollmentPercent":10.2,"waitlistCount":0},{"day":24,"date":"2026-04-14","enrolledCount":25,"enrollmentPercent":11.1,"waitlistCount":0},{"day":24,"date":"2026-04-14","enrolledCount":32,"enrollmentPercent":14.2,"waitlistCount":0},{"day":24,"date":"2026-04-14","enrolledCount":34,"enrollmentPercent":15.1,"waitlistCount":0},{"day":24,"date":"2026-04-14","enrolledCount":37,"enrollmentPercent":16.4,"waitlistCount":0},{"day":24,"date":"2026-04-15","enrolledCount":38,"enrollmentPercent":16.9,"waitlistCount":0},{"day":24,"date":"2026-04-15","enrolledCount":39,"enrollmentPercent":17.3,"waitlistCount":0},{"day":25,"date":"2026-04-15","enrolledCount":38,"enrollmentPercent":16.9,"waitlistCount":0},{"day":25,"date":"2026-04-15","enrolledCount":44,"enrollmentPercent":19.6,"waitlistCount":0},{"day":25,"date":"2026-04-15","enrolledCount":46,"enrollmentPercent":20.4,"waitlistCount":0},{"day":25,"date":"2026-04-15","enrolledCount":48,"enrollmentPercent":21.3,"waitlistCount":0},{"day":25,"date":"2026-04-15","enrolledCount":56,"enrollmentPercent":24.9,"waitlistCount":0},{"day":25,"date":"2026-04-15","enrolledCount":59,"enrollmentPercent":26.2,"waitlistCount":0},{"day":25,"date":"2026-04-15","enrolledCount":63,"enrollmentPercent":28,"waitlistCount":0},{"day":25,"date":"2026-04-15","enrolledCount":64,"enrollmentPercent":28.4,"waitlistCount":0},{"day":25,"date":"2026-04-15","enrolledCount":67,"enrollmentPercent":29.8,"waitlistCount":0},{"day":25,"date":"2026-04-15","enrolledCount":68,"enrollmentPercent":30.2,"waitlistCount":0},{"day":25,"date":"2026-04-15","enrolledCount":67,"enrollmentPercent":29.8,"waitlistCount":0},{"day":25,"date":"2026-04-16","enrolledCount":66,"enrollmentPercent":29.3,"waitlistCount":0},{"day":25,"date":"2026-04-16","enrolledCount":67,"enrollmentPercent":29.8,"waitlistCount":0},{"day":26,"date":"2026-04-16","enrolledCount":67,"enrollmentPercent":29.8,"waitlistCount":0},{"day":26,"date":"2026-04-16","enrolledCount":66,"enrollmentPercent":29.3,"waitlistCount":0},{"day":26,"date":"2026-04-16","enrolledCount":70,"enrollmentPercent":31.1,"waitlistCount":0},{"day":26,"date":"2026-04-16","enrolledCount":72,"enrollmentPercent":32,"waitlistCount":0},{"day":26,"date":"2026-04-16","enrolledCount":75,"enrollmentPercent":33.3,"waitlistCount":0},{"day":26,"date":"2026-04-16","enrolledCount":81,"enrollmentPercent":36,"waitlistCount":0},{"day":26,"date":"2026-04-16","enrolledCount":87,"enrollmentPercent":38.7,"waitlistCount":0},{"day":26,"date":"2026-04-16","enrolledCount":94,"enrollmentPercent":41.8,"waitlistCount":0},{"day":26,"date":"2026-04-17","enrolledCount":93,"enrollmentPercent":41.3,"waitlistCount":0},{"day":26,"date":"2026-04-17","enrolledCount":96,"enrollmentPercent":42.7,"waitlistCount":0},{"day":26,"date":"2026-04-17","enrolledCount":97,"enrollmentPercent":43.1,"waitlistCount":0},{"day":27,"date":"2026-04-17","enrolledCount":102,"enrollmentPercent":45.3,"waitlistCount":0},{"day":27,"date":"2026-04-17","enrolledCount":112,"enrollmentPercent":49.8,"waitlistCount":3},{"day":27,"date":"2026-04-17","enrolledCount":114,"enrollmentPercent":50.7,"waitlistCount":3},{"day":27,"date":"2026-04-17","enrolledCount":114,"enrollmentPercent":50.7,"waitlistCount":4},{"day":27,"date":"2026-04-17","enrolledCount":118,"enrollmentPercent":52.4,"waitlistCount":1},{"day":27,"date":"2026-04-17","enrolledCount":117,"enrollmentPercent":52,"waitlistCount":1},{"day":27,"date":"2026-04-17","enrolledCount":117,"enrollmentPercent":52,"waitlistCount":2},{"day":27,"date":"2026-04-17","enrolledCount":119,"enrollmentPercent":52.9,"waitlistCount":0},{"day":27,"date":"2026-04-18","enrolledCount":120,"enrollmentPercent":53.3,"waitlistCount":0}],"enrollmentHistoryBySemester":{"Fall 2025":[{"day":1,"date":"2025-04-03","enrolledCount":202,"enrollmentPercent":99,"waitlistCount":0},{"day":219,"date":"2025-11-08","enrolledCount":0,"enrollmentPercent":0,"waitlistCount":0},{"day":223,"date":"2025-11-12","enrolledCount":0,"enrollmentPercent":0,"waitlistCount":0},{"day":228,"date":"2025-11-17","enrolledCount":0,"enrollmentPercent":0,"waitlistCount":0},{"day":230,"date":"2025-11-19","enrolledCount":0,"enrollmentPercent":0,"waitlistCount":0},{"day":230,"date":"2025-11-19","enrolledCount":0,"enrollmentPercent":0,"waitlistCount":0},{"day":231,"date":"2025-11-19","enrolledCount":0,"enrollmentPercent":0,"waitlistCount":0},{"day":252,"date":"2025-12-10","enrolledCount":0,"enrollmentPercent":0,"waitlistCount":0},{"day":256,"date":"2025-12-15","enrolledCount":0,"enrollmentPercent":0,"waitlistCount":0}],"Fall 2024":[{"day":1,"date":"2024-04-04","enrolledCount":0,"enrollmentPercent":0,"waitlistCount":0},{"day":20,"date":"2024-04-23","enrolledCount":18,"enrollmentPercent":9,"waitlistCount":0},{"day":21,"date":"2024-04-24","enrolledCount":39,"enrollmentPercent":19.5,"waitlistCount":0},{"day":22,"date":"2024-04-25","enrolledCount":58,"enrollmentPercent":29,"waitlistCount":0},{"day":23,"date":"2024-04-26","enrolledCount":76,"enrollmentPercent":38,"waitlistCount":0},{"day":24,"date":"2024-04-27","enrolledCount":92,"enrollmentPercent":46,"waitlistCount":0},{"day":26,"date":"2024-04-29","enrolledCount":95,"enrollmentPercent":47.5,"waitlistCount":0},{"day":27,"date":"2024-04-30","enrolledCount":96,"enrollmentPercent":48,"waitlistCount":0},{"day":28,"date":"2024-05-01","enrolledCount":101,"enrollmentPercent":50.5,"waitlistCount":0},{"day":30,"date":"2024-05-03","enrolledCount":103,"enrollmentPercent":51.5,"waitlistCount":0},{"day":31,"date":"2024-05-04","enrolledCount":102,"enrollmentPercent":51,"waitlistCount":0},{"day":33,"date":"2024-05-06","enrolledCount":104,"enrollmentPercent":52,"waitlistCount":0},{"day":34,"date":"2024-05-07","enrolledCount":105,"enrollmentPercent":52.5,"waitlistCount":0},{"day":35,"date":"2024-05-08","enrolledCount":106,"enrollmentPercent":53,"waitlistCount":0},{"day":36,"date":"2024-05-09","enrolledCount":107,"enrollmentPercent":53.5,"waitlistCount":0},{"day":39,"date":"2024-05-12","enrolledCount":108,"enrollmentPercent":54,"waitlistCount":0},{"day":42,"date":"2024-05-15","enrolledCount":109,"enrollmentPercent":54.5,"waitlistCount":0},{"day":43,"date":"2024-05-16","enrolledCount":110,"enrollmentPercent":55,"waitlistCount":0},{"day":44,"date":"2024-05-17","enrolledCount":112,"enrollmentPercent":56,"waitlistCount":0},{"day":45,"date":"2024-05-18","enrolledCount":110,"enrollmentPercent":55,"waitlistCount":0},{"day":47,"date":"2024-05-20","enrolledCount":111,"enrollmentPercent":55.5,"waitlistCount":0},{"day":48,"date":"2024-05-21","enrolledCount":110,"enrollmentPercent":55,"waitlistCount":0},{"day":49,"date":"2024-05-22","enrolledCount":112,"enrollmentPercent":56,"waitlistCount":0},{"day":51,"date":"2024-05-24","enrolledCount":113,"enrollmentPercent":56.5,"waitlistCount":0},{"day":52,"date":"2024-05-25","enrolledCount":114,"enrollmentPercent":57,"waitlistCount":0},{"day":53,"date":"2024-05-26","enrolledCount":115,"enrollmentPercent":57.5,"waitlistCount":0},{"day":58,"date":"2024-05-31","enrolledCount":116,"enrollmentPercent":58,"waitlistCount":0},{"day":62,"date":"2024-06-04","enrolledCount":117,"enrollmentPercent":58.5,"waitlistCount":0},{"day":69,"date":"2024-06-11","enrolledCount":119,"enrollmentPercent":59.5,"waitlistCount":0},{"day":70,"date":"2024-06-12","enrolledCount":120,"enrollmentPercent":60,"waitlistCount":0},{"day":71,"date":"2024-06-13","enrolledCount":121,"enrollmentPercent":60.5,"waitlistCount":0},{"day":136,"date":"2024-08-17","enrolledCount":200,"enrollmentPercent":100,"waitlistCount":7},{"day":139,"date":"2024-08-20","enrolledCount":200,"enrollmentPercent":100,"waitlistCount":8},{"day":140,"date":"2024-08-21","enrolledCount":199,"enrollmentPercent":99.5,"waitlistCount":8},{"day":141,"date":"2024-08-22","enrolledCount":199,"enrollmentPercent":99.5,"waitlistCount":10},{"day":142,"date":"2024-08-23","enrolledCount":199,"enrollmentPercent":99.5,"waitlistCount":11},{"day":143,"date":"2024-08-24","enrolledCount":200,"enrollmentPercent":100,"waitlistCount":11},{"day":145,"date":"2024-08-26","enrolledCount":200,"enrollmentPercent":100,"waitlistCount":10},{"day":147,"date":"2024-08-28","enrolledCount":204,"enrollmentPercent":100,"waitlistCount":5},{"day":148,"date":"2024-08-29","enrolledCount":203,"enrollmentPercent":99.5,"waitlistCount":5},{"day":150,"date":"2024-08-31","enrolledCount":204,"enrollmentPercent":100,"waitlistCount":5},{"day":151,"date":"2024-09-01","enrolledCount":204,"enrollmentPercent":100,"waitlistCount":6},{"day":154,"date":"2024-09-04","enrolledCount":204,"enrollmentPercent":100,"waitlistCount":7},{"day":155,"date":"2024-09-05","enrolledCount":205,"enrollmentPercent":100.5,"waitlistCount":6},{"day":156,"date":"2024-09-06","enrolledCount":207,"enrollmentPercent":101.5,"waitlistCount":3},{"day":157,"date":"2024-09-07","enrolledCount":208,"enrollmentPercent":102,"waitlistCount":1},{"day":159,"date":"2024-09-09","enrolledCount":207,"enrollmentPercent":101.5,"waitlistCount":1},{"day":161,"date":"2024-09-11","enrolledCount":206,"enrollmentPercent":101,"waitlistCount":1},{"day":162,"date":"2024-09-12","enrolledCount":206,"enrollmentPercent":101,"waitlistCount":2},{"day":163,"date":"2024-09-13","enrolledCount":204,"enrollmentPercent":100,"waitlistCount":2},{"day":164,"date":"2024-09-14","enrolledCount":203,"enrollmentPercent":99.5,"waitlistCount":2},{"day":167,"date":"2024-09-17","enrolledCount":204,"enrollmentPercent":100,"waitlistCount":1},{"day":168,"date":"2024-09-18","enrolledCount":203,"enrollmentPercent":99.5,"waitlistCount":1},{"day":169,"date":"2024-09-19","enrolledCount":202,"enrollmentPercent":99,"waitlistCount":2},{"day":171,"date":"2024-09-21","enrolledCount":203,"enrollmentPercent":99.5,"waitlistCount":1},{"day":174,"date":"2024-09-24","enrolledCount":202,"enrollmentPercent":99,"waitlistCount":0}]}}