{"gradeHistory":[{"semester":"Fall 2025","instructor":"John Dougherty","totalEnrolled":35,"distribution":{"aPlus":0,"a":25,"aMinus":4,"bPlus":1,"b":1,"bMinus":0,"cPlus":0,"c":1,"cMinus":0,"dPlus":0,"d":0,"dMinus":1,"f":1,"p":1,"np":0},"averageGPA":3.6411764705882352},{"semester":"Fall 2024","instructor":"John Dougherty","totalEnrolled":30,"distribution":{"aPlus":0,"a":27,"aMinus":0,"bPlus":0,"b":0,"bMinus":2,"cPlus":0,"c":0,"cMinus":0,"dPlus":0,"d":0,"dMinus":0,"f":1,"p":0,"np":0},"averageGPA":3.7800000000000002},{"semester":"Fall 2023","instructor":"John Dougherty","totalEnrolled":37,"distribution":{"aPlus":0,"a":31,"aMinus":1,"bPlus":0,"b":0,"bMinus":0,"cPlus":0,"c":1,"cMinus":0,"dPlus":0,"d":0,"dMinus":1,"f":2,"p":0,"np":1},"averageGPA":3.622222222222222},{"semester":"Fall 2022","instructor":"John Dougherty","totalEnrolled":35,"distribution":{"aPlus":0,"a":32,"aMinus":0,"bPlus":0,"b":0,"bMinus":1,"cPlus":0,"c":0,"cMinus":0,"dPlus":0,"d":0,"dMinus":0,"f":1,"p":0,"np":1},"averageGPA":3.844117647058823},{"semester":"Fall 2021","instructor":"Beth Piatote","totalEnrolled":37,"distribution":{"aPlus":0,"a":16,"aMinus":7,"bPlus":0,"b":5,"bMinus":0,"cPlus":2,"c":0,"cMinus":0,"dPlus":0,"d":0,"dMinus":0,"f":2,"p":4,"np":1},"averageGPA":3.421875},{"semester":"Fall 2020","instructor":"Enrique Lima","totalEnrolled":30,"distribution":{"aPlus":0,"a":16,"aMinus":5,"bPlus":3,"b":0,"bMinus":1,"cPlus":1,"c":0,"cMinus":0,"dPlus":0,"d":0,"dMinus":0,"f":2,"p":2,"np":0},"averageGPA":3.478571428571428},{"semester":"Fall 2019","instructor":"Enrique Lima","totalEnrolled":31,"distribution":{"aPlus":0,"a":22,"aMinus":2,"bPlus":1,"b":0,"bMinus":0,"cPlus":0,"c":0,"cMinus":0,"dPlus":0,"d":0,"dMinus":0,"f":0,"p":6,"np":0},"averageGPA":3.948}],"enrollmentHistory":[{"day":1,"date":"2026-03-22","enrolledCount":0,"enrollmentPercent":0,"waitlistCount":0},{"day":4,"date":"2026-03-25","enrolledCount":0,"enrollmentPercent":0,"waitlistCount":0},{"day":5,"date":"2026-03-27","enrolledCount":0,"enrollmentPercent":0,"waitlistCount":0},{"day":6,"date":"2026-03-28","enrolledCount":0,"enrollmentPercent":0,"waitlistCount":0},{"day":13,"date":"2026-04-03","enrolledCount":0,"enrollmentPercent":0,"waitlistCount":0},{"day":18,"date":"2026-04-08","enrolledCount":0,"enrollmentPercent":0,"waitlistCount":0},{"day":23,"date":"2026-04-13","enrolledCount":1,"enrollmentPercent":2.9,"waitlistCount":0},{"day":23,"date":"2026-04-13","enrolledCount":2,"enrollmentPercent":5.7,"waitlistCount":0},{"day":23,"date":"2026-04-13","enrolledCount":2,"enrollmentPercent":5.7,"waitlistCount":0},{"day":23,"date":"2026-04-14","enrolledCount":2,"enrollmentPercent":5.7,"waitlistCount":0},{"day":23,"date":"2026-04-14","enrolledCount":2,"enrollmentPercent":5.7,"waitlistCount":0},{"day":24,"date":"2026-04-14","enrolledCount":3,"enrollmentPercent":8.6,"waitlistCount":0},{"day":25,"date":"2026-04-15","enrolledCount":4,"enrollmentPercent":11.4,"waitlistCount":0},{"day":26,"date":"2026-04-16","enrolledCount":5,"enrollmentPercent":14.3,"waitlistCount":0},{"day":26,"date":"2026-04-16","enrolledCount":6,"enrollmentPercent":17.1,"waitlistCount":0},{"day":27,"date":"2026-04-17","enrolledCount":7,"enrollmentPercent":20,"waitlistCount":0}],"enrollmentHistoryBySemester":{}}